README.md
setup.cfg
setup.py
tmi/DB.py
tmi/Room.py
tmi/RoomManager.py
tmi/__init__.py
tmi/tmi.py
tmi.egg-info/PKG-INFO
tmi.egg-info/SOURCES.txt
tmi.egg-info/dependency_links.txt
tmi.egg-info/entry_points.txt
tmi.egg-info/not-zip-safe
tmi.egg-info/requires.txt
tmi.egg-info/top_level.txt