Metadata-Version: 2.1
Name: tmi
Version: 0.6.622
Summary: NoStress team (2018 HU-OSS B-6)'s Open Source CLI Todo List
Home-page: https://github.com/onnoo/TMI
Author: onnoo
Author-email: sweyjw@gmail.com
License: UNKNOWN
Download-URL: https://github.com/onnoo/TMI/archive/master.tar.gz
Keywords: tmi,todo list,todo cli
Platform: UNKNOWN
Classifier: License :: OSI Approved :: MIT License
Classifier: Programming Language :: Python :: 3
Classifier: Programming Language :: Python :: 3.2
Classifier: Programming Language :: Python :: 3.3
Classifier: Programming Language :: Python :: 3.4
Classifier: Programming Language :: Python :: 3.5
Classifier: Programming Language :: Python :: 3.6
Requires-Python: >=3
